LICENSE
MANIFEST.in
README.rst
setup.py
unipag/__init__.py
unipag/config.py
unipag/exceptions.py
unipag/models.py
unipag/transport.py
unipag/version.py
unipag.egg-info/PKG-INFO
unipag.egg-info/SOURCES.txt
unipag.egg-info/dependency_links.txt
unipag.egg-info/not-zip-safe
unipag.egg-info/requires.txt
unipag.egg-info/top_level.txt