Metadata-Version: 1.1
Name: unipag
Version: 0.2.0
Summary: Unipag Client for Python
Home-page: https://github.com/unipag/unipag-python
Author: Denis Stebunov
Author-email: support@unipag.com
License: The ISC License
